{
	"id": -1,
	"name": "Annoying Dog dressed with the Bonhomme Carnaval's clothes.",
	"description": "The character representing indie developer of Deltarune and Undertale ''Toby Fox'' dressed with the arrowed sash and the toque of the character representing the Quebec Winter Carnaval : The Bonhomme Carnaval",
	"links": {
		"subreddit": [
			"quebec",
			"deltarune",
			"undertale"
		],
		"discord": [
			"placequebec",
			"undertale"
		]
	},
	"path": {
		"179-214": [
			[
				796,
				187
			],
			[
				798,
				187
			],
			[
				798,
				186
			],
			[
				798,
				185
			],
			[
				799,
				185
			],
			[
				799,
				184
			],
			[
				800,
				184
			],
			[
				800,
				183
			],
			[
				801,
				183
			],
			[
				801,
				182
			],
			[
				801,
				181
			],
			[
				802,
				181
			],
			[
				802,
				180
			],
			[
				803,
				180
			],
			[
				803,
				179
			],
			[
				803,
				178
			],
			[
				803,
				177
			],
			[
				802,
				177
			],
			[
				802,
				176
			],
			[
				801,
				176
			],
			[
				801,
				175
			],
			[
				800,
				175
			],
			[
				800,
				174
			],
			[
				799,
				174
			],
			[
				770,
				174
			],
			[
				769,
				174
			],
			[
				769,
				175
			],
			[
				769,
				176
			],
			[
				770,
				176
			],
			[
				771,
				176
			],
			[
				773,
				176
			],
			[
				775,
				176
			],
			[
				776,
				176
			],
			[
				776,
				176
			],
			[
				776,
				177
			],
			[
				777,
				177
			],
			[
				778,
				177
			],
			[
				778,
				178
			],
			[
				778,
				179
			],
			[
				778,
				180
			],
			[
				778,
				181
			],
			[
				778,
				182
			],
			[
				779,
				182
			],
			[
				779,
				183
			],
			[
				778,
				183
			],
			[
				778,
				184
			],
			[
				777,
				184
			],
			[
				777,
				185
			],
			[
				778,
				186
			],
			[
				779,
				187
			],
			[
				780,
				187
			],
			[
				781,
				187
			],
			[
				782,
				187
			],
			[
				784,
				187
			],
			[
				784,
				187
			],
			[
				785,
				187
			],
			[
				785,
				186
			],
			[
				785,
				185
			],
			[
				786,
				185
			],
			[
				787,
				185
			],
			[
				788,
				185
			],
			[
				789,
				185
			],
			[
				790,
				185
			],
			[
				791,
				185
			],
			[
				792,
				185
			],
			[
				792,
				184
			],
			[
				793,
				184
			],
			[
				794,
				184
			],
			[
				796,
				184
			],
			[
				797,
				184
			],
			[
				798,
				184
			],
			[
				798,
				184
			],
			[
				799,
				184
			],
			[
				800,
				183
			],
			[
				798,
				184
			],
			[
				798,
				184
			],
			[
				798,
				184
			],
			[
				798,
				184
			],
			[
				798,
				184
			],
			[
				797,
				184
			],
			[
				798,
				184
			],
			[
				796,
				185
			],
			[
				797,
				184
			],
			[
				796,
				184
			],
			[
				796,
				184
			],
			[
				796,
				184
			],
			[
				795,
				184
			],
			[
				798,
				183
			],
			[
				799,
				183
			],
			[
				799,
				182
			],
			[
				800,
				183
			]
		]
	},
	"center": {
		"179-214": [
			788,
			179
		]
	}
}
